Workbook

Sheet Data 
B2: Date | C2: Category | D2: Payment Mode | E2: Amount | F2: Month | G2: Month No
B3: 46259 | C3: Travel | D3: UPI | E3: 1200 | F3: =TEXT(B3,"MMM") -> Aug | G3: =MONTH(B3) -> 8
B4: 46120 | C4: Food | D4: UPI | E4: 420 | F4: =TEXT(B4,"MMM") -> Apr | G4: =MONTH(B4) -> 4
B5: 46106 | C5: Rent | D5: Card | E5: 6000 | F5: =TEXT(B5,"MMM") -> Mar | G5: =MONTH(B5) -> 3
B6: 46163 | C6: Fun | D6: UPI | E6: 280 | F6: =TEXT(B6,"MMM") -> May | G6: =MONTH(B6) -> 5
B7: 46287 | C7: Travel | D7: Cash | E7: 70 | F7: =TEXT(B7,"MMM") -> Sep | G7: =MONTH(B7) -> 9
B8: 46284 | C8: Study | D8: Card | E8: 500 | F8: =TEXT(B8,"MMM") -> Sep | G8: =MONTH(B8) -> 9
B9: 46288 | C9: Travel | D9: Cash | E9: 70 | F9: =TEXT(B9,"MMM") -> Sep | G9: =MONTH(B9) -> 9
B10: 46098 | C10: Rent | D10: Cash | E10: 3600 | F10: =TEXT(B10,"MMM") -> Mar | G10: =MONTH(B10) -> 3
B11: 46079 | C11: Rent | D11: Card | E11: 3000 | F11: =TEXT(B11,"MMM") -> Feb | G11: =MONTH(B11) -> 2
B12: 46198 | C12: Food | D12: UPI | E12: 120 | F12: =TEXT(B12,"MMM") -> Jun | G12: =MONTH(B12) -> 6
B13: 46285 | C13: Study | D13: Cash | E13: 160 | F13: =TEXT(B13,"MMM") -> Sep | G13: =MONTH(B13) -> 9
B14: 46241 | C14: Travel | D14: UPI | E14: 60 | F14: =TEXT(B14,"MMM") -> Aug | G14: =MONTH(B14) -> 8
... B50: 46147 | C50: Travel | D50: UPI | E50: 1280 | F50: =TEXT(B50,"MMM") -> May | G50: =MONTH(B50) -> 5

Sheet Summary
B3: Total spend | C3: =SUM('Data '!E3:E50) -> 50443
B5: Average spend | C5: =AVERAGE('Data '!E3:E50) -> 1050.8958
B7: Highest expense | C7: =MAX('Data '!E3:E50) -> 6000
B9: Lowest expense | C9: =MIN('Data '!E3:E50) -> 50
B11: Transactions | C11: =COUNT('Data '!E3:E50) -> 48
B14: Category | C14: Total | D14: Count | E14: Average
B15: Food | C15: =SUMIF('Data '!$C$3:$C$50,Summary!B15,'Data '!$E$3:$E$50) -> 2220 | D15: =COUNTIF('Data '!$C$3:$C$50,Summary!B15) -> 10 | E15: =AVERAGEIF('Data '!$C$3:$C$50,Summary!B15,'Data '!$E$3:$E$50) -> 222
B16: Travel | C16: =SUMIF('Data '!$C$3:$C$50,Summary!B16,'Data '!$E$3:$E$50) -> 5670 | D16: =COUNTIF('Data '!$C$3:$C$50,Summary!B16) -> 12 | E16: =AVERAGEIF('Data '!$C$3:$C$50,Summary!B16,'Data '!$E$3:$E$50) -> 472.5
B17: Rent | C17: =SUMIF('Data '!$C$3:$C$50,Summary!B17,'Data '!$E$3:$E$50) -> 38100 | D17: =COUNTIF('Data '!$C$3:$C$50,Summary!B17) -> 10 | E17: =AVERAGEIF('Data '!$C$3:$C$50,Summary!B17,'Data '!$E$3:$E$50) -> 3810
B18: Study | C18: =SUMIF('Data '!$C$3:$C$50,Summary!B18,'Data '!$E$3:$E$50) -> 2923 | D18: =COUNTIF('Data '!$C$3:$C$50,Summary!B18) -> 11 | E18: =AVERAGEIF('Data '!$C$3:$C$50,Summary!B18,'Data '!$E$3:$E$50) -> 265.72727
B19: Fun | C19: =SUMIF('Data '!$C$3:$C$50,Summary!B19,'Data '!$E$3:$E$50) -> 1530 | D19: =COUNTIF('Data '!$C$3:$C$50,Summary!B19) -> 5 | E19: =AVERAGEIF('Data '!$C$3:$C$50,Summary!B19,'Data '!$E$3:$E$50) -> 306

Sheet Budget
B2: Category | C2: Budget | D2: Actual | E2: Difference | F2: Status
B3: Food | C3: 2500 | D3: =SUMIF('Data '!C3:C50,Budget!B3,'Data '!E3:E50) -> 2220 | E3: =C3-D3 -> 280 | F3: =IF(D3>C3,"Over Budget","Within Budget") -> Within Budget
B4: Travel | C4: 3500 | D4: =SUMIF('Data '!C4:C51,Budget!B4,'Data '!E4:E51) -> 4470 | E4: =C4-D4 -> -970 | F4: =IF(D4>C4,"Over Budget","Within Budget") -> Over Budget
B5: Rent | C5: 30000 | D5: =SUMIF('Data '!C5:C52,Budget!B5,'Data '!E5:E52) -> 38100 | E5: =C5-D5 -> -8100 | F5: =IF(D5>C5,"Over Budget","Within Budget") -> Over Budget
B6: Study | C6: 4000 | D6: =SUMIF('Data '!C6:C53,Budget!B6,'Data '!E6:E53) -> 2923 | E6: =C6-D6 -> 1077 | F6: =IF(D6>C6,"Over Budget","Within Budget") -> Within Budget
B7: Fun | C7: 1000 | D7: =SUMIF('Data '!C7:C54,Budget!B7,'Data '!E7:E54) -> 1250 | E7: =C7-D7 -> -250 | F7: =IF(D7>C7,"Over Budget","Within Budget") -> Over Budget

Sheet Pivot
A1: Month | B1: All
A3: Sum of Amount | B3: Column Labels
A4: Row Labels | B4: Card | C4: Cash | D4: UPI | E4: Grand Total
A5: Food | C5: 1160 | D5: 1060 | E5: 2220
A6: Fun | B6: 500 | C6: 250 | D6: 780 | E6: 1530
A7: Rent | B7: 12000 | C7: 10100 | D7: 16000 | E7: 38100
A8: Study | B8: 1799 | C8: 804 | D8: 320 | E8: 2923
A9: Travel | B9: 2150 | C9: 810 | D9: 2710 | E9: 5670
A10: Grand Total | B10: 16449 | C10: 13124 | D10: 20870 | E10: 50443

Sheet Dashboard
F4: Expense Dashboard 2026
F6: Total spend | G6: =Summary!C3 -> 50443
F7: Average spend | G7: =ROUND(Summary!C5,0) -> 1051
F8: Transactions | G8: =Summary!C11 -> 48
F9: Categories over budget | G9: =COUNTIF(Budget!F3:F7,"Over Budget") -> 3
